mempool_mcp/__init__.py
mempool_mcp/client.py
mempool_mcp/server.py
mempool_mcp/tools/__init__.py
mempool_mcp/tools/addresses.py
mempool_mcp/tools/blocks.py
mempool_mcp/tools/general.py
mempool_mcp/tools/lightning.py
mempool_mcp/tools/mempool.py
mempool_mcp/tools/mining.py
mempool_mcp/tools/transactions.py
mempool_mcp-0.1.4.dist-info/METADATA
mempool_mcp-0.1.4.dist-info/WHEEL
mempool_mcp-0.1.4.dist-info/entry_points.txt
mempool_mcp-0.1.4.dist-info/licenses/LICENSE
mempool_mcp-0.1.4.dist-info/RECORD
