Metadata-Version: 2.4
Name: mempool-mcp
Version: 0.1.4
Summary: MCP server for Mempool.space Bitcoin explorer API
Author: BitcoinMonk
License-Expression: MIT
License-File: LICENSE
Requires-Python: >=3.11
Requires-Dist: httpx-socks>=0.9.0
Requires-Dist: httpx>=0.27.0
Requires-Dist: mcp>=1.0.0
Provides-Extra: dev
Requires-Dist: pytest-asyncio>=0.23.0; extra == 'dev'
Requires-Dist: pytest>=8.0.0; extra == 'dev'
